JLua/TestSources.py
JLua/__init__.py
JLua/__main__.py
JLua_basic_DrSamse-0.2.0.dist-info/LICENCE
JLua_basic_DrSamse-0.2.0.dist-info/METADATA
JLua_basic_DrSamse-0.2.0.dist-info/WHEEL
JLua_basic_DrSamse-0.2.0.dist-info/top_level.txt
JLua_basic_DrSamse-0.2.0.dist-info/RECORD
