Metadata-Version: 2.1
Name: JLua-basic-DrSamse
Version: 0.2.0
Summary: A Package for Json-like Lua usement in python
Home-page: https://github.com/DrSamse/JLua
Author: Samuel Nösslböck
Author-email: samuel.noesslboeck@gmail.com
License: UNKNOWN
Platform: UNKNOWN
Classifier: Programming Language :: Python :: 3
Classifier: License :: OSI Approved :: MIT License
Classifier: Operating System :: OS Independent
Requires-Python: >=3.6
Requires-Dist: lupa
